Metadata-Version: 1.0
Name: formula1-collector
Version: 0.4.2
Summary: A library for realtime formula 1 data
Home-page: https://github.com/kithuto/formula-1-collector
Author: Ignasi Rovira
Author-email: UNKNOWN
License: MIT
Platform: UNKNOWN
